COPYING
LICENCE
MANIFEST.in
NEWS
README
setup.py
business_tools/__init__.py
business_tools/bank_account.py
business_tools/business_id.py
business_tools/money.py
business_tools/reference_number.py
business_tools.egg-info/PKG-INFO
business_tools.egg-info/SOURCES.txt
business_tools.egg-info/dependency_links.txt
business_tools.egg-info/top_level.txt
business_tools/tests/__init__.py
business_tools/tests/test_bank_account.py
business_tools/tests/test_business_id.py
business_tools/tests/test_money.py
business_tools/tests/test_reference_number.py