Metadata-Version: 1.0
Name: business-tools
Version: 0.2.14
Summary: A python module for various business transactions.
Home-page: UNKNOWN
Author: Norfello Oy
Author-email: opensource@norfello.com
License: BSD
Platform: UNKNOWN
Classifier: Intended Audience :: Developers
Classifier: Intended Audience :: Financial and Insurance Industry
Classifier: License :: OSI Approved :: BSD License
Classifier: Programming Language :: Python
Classifier: Topic :: Office/Business
